{
  "inbound": [
    {
      "localPort": 10808,
      "protocol": "socks",
      "udpEnabled": true,
      "sniffingEnabled": true
    }
  ],
  "logEnabled": false,
  "loglevel": "warning",
  "index": 0,
  "vmess": [
    {
      "configVersion": 2,
      "address": "sd.mdss.cloud",
      "port": 10086,
      "id": "dcf8e5eb-3805-3a18-8d0d-5fa0a7ddce38",
      "alterId": 0,
      "security": "auto",
      "network": "tcp",
      "remarks": "剩余流量：299.86GB",
      "headerType": "none",
      "requestHost": "",
      "path": "",
      "streamSecurity": "",
      "allowInsecure": "False",
      "configType": 1,
      "testResult": "",
      "subid": "199ab9f3-c6f5-4c95-8d87-b26a9ed0050a",
      "flow": "",
      "sni": "",
      "alpn": []
    },
    {
      "configVersion": 2,
      "address": "sd.mdss.cloud",
      "port": 10086,
      "id": "dcf8e5eb-3805-3a18-8d0d-5fa0a7ddce38",
      "alterId": 0,
      "security": "auto",
      "network": "tcp",
      "remarks": "过期时间：2022-07-04",
      "headerType": "none",
      "requestHost": "",
      "path": "",
      "streamSecurity": "",
      "allowInsecure": "False",
      "configType": 1,
      "testResult": "",
      "subid": "199ab9f3-c6f5-4c95-8d87-b26a9ed0050a",
      "flow": "",
      "sni": "",
      "alpn": []
    },
    {
      "configVersion": 2,
      "address": "lrnodes.sd-yun.cc",
      "port": 10028,
      "id": "dcf8e5eb-3805-3a18-8d0d-5fa0a7ddce38",
      "alterId": 0,
      "security": "auto",
      "network": "ws",
      "remarks": "A懒人节点",
      "headerType": "none",
      "requestHost": "www.bing.com",
      "path": "/",
      "streamSecurity": "",
      "allowInsecure": "False",
      "configType": 1,
      "testResult": "",
      "subid": "199ab9f3-c6f5-4c95-8d87-b26a9ed0050a",
      "flow": "",
      "sni": "",
      "alpn": []
    },
    {
      "configVersion": 2,
      "address": "ru-l1-hn.sd-yun.cc",
      "port": 34131,
      "id": "dcf8e5eb-3805-3a18-8d0d-5fa0a7ddce38",
      "alterId": 0,
      "security": "auto",
      "network": "ws",
      "remarks": "俄罗斯L1 中继M1S1 [0.5]",
      "headerType": "none",
      "requestHost": "www.bing.com",
      "path": "/",
      "streamSecurity": "",
      "allowInsecure": "False",
      "configType": 1,
      "testResult": "",
      "subid": "199ab9f3-c6f5-4c95-8d87-b26a9ed0050a",
      "flow": "",
      "sni": "",
      "alpn": []
    },
    {
      "configVersion": 2,
      "address": "ru-l1-hn.sd-yun.cc",
      "port": 30004,
      "id": "dcf8e5eb-3805-3a18-8d0d-5fa0a7ddce38",
      "alterId": 0,
      "security": "auto",
      "network": "ws",
      "remarks": "俄罗斯L1 中继M1S2 [0.5]",
      "headerType": "none",
      "requestHost": "www.bing.com",
      "path": "/",
      "streamSecurity": "",
      "allowInsecure": "False",
      "configType": 1,
      "testResult": "",
      "subid": "199ab9f3-c6f5-4c95-8d87-b26a9ed0050a",
      "flow": "",
      "sni": "",
      "alpn": []
    },
    {
      "configVersion": 2,
      "address": "ru-l2-hn.sd-yun.cc",
      "port": 34123,
      "id": "dcf8e5eb-3805-3a18-8d0d-5fa0a7ddce38",
      "alterId": 0,
      "security": "auto",
      "network": "ws",
      "remarks": "俄罗斯L2 中继M1S1 [0.5]\t",
      "headerType": "none",
      "requestHost": "www.bing.com",
      "path": "/",
      "streamSecurity": "",
      "allowInsecure": "False",
      "configType": 1,
      "testResult": "",
      "subid": "199ab9f3-c6f5-4c95-8d87-b26a9ed0050a",
      "flow": "",
      "sni": "",
      "alpn": []
    },
    {
      "configVersion": 2,
      "address": "ru-l2-hn.sd-yun.cc",
      "port": 34112,
      "id": "dcf8e5eb-3805-3a18-8d0d-5fa0a7ddce38",
      "alterId": 0,
      "security": "auto",
      "network": "ws",
      "remarks": "俄罗斯L2 中继M1S2 [0.5]\t",
      "headerType": "none",
      "requestHost": "www.bing.com",
      "path": "/",
      "streamSecurity": "",
      "allowInsecure": "False",
      "configType": 1,
      "testResult": "",
      "subid": "199ab9f3-c6f5-4c95-8d87-b26a9ed0050a",
      "flow": "",
      "sni": "",
      "alpn": []
    },
    {
      "configVersion": 2,
      "address": "tw001.dynu.net",
      "port": 28081,
      "id": "dcf8e5eb-3805-3a18-8d0d-5fa0a7ddce38",
      "alterId": 0,
      "security": "auto",
      "network": "ws",
      "remarks": "台湾 A | 公益节点 直连 1倍 NF【最新网址 闪电.net】",
      "headerType": "none",
      "requestHost": "www.bing.com",
      "path": "/",
      "streamSecurity": "",
      "allowInsecure": "False",
      "configType": 1,
      "testResult": "",
      "subid": "199ab9f3-c6f5-4c95-8d87-b26a9ed0050a",
      "flow": "",
      "sni": "",
      "alpn": []
    },
    {
      "configVersion": 2,
      "address": "tw002.dynu.net",
      "port": 28081,
      "id": "dcf8e5eb-3805-3a18-8d0d-5fa0a7ddce38",
      "alterId": 0,
      "security": "auto",
      "network": "ws",
      "remarks": "台湾 B | 公益节点 直连 1倍 NF【最新网址 闪电.net】",
      "headerType": "none",
      "requestHost": "www.bing.com",
      "path": "/",
      "streamSecurity": "",
      "allowInsecure": "False",
      "configType": 1,
      "testResult": "",
      "subid": "199ab9f3-c6f5-4c95-8d87-b26a9ed0050a",
      "flow": "",
      "sni": "",
      "alpn": []
    },
    {
      "configVersion": 2,
      "address": "tw003.dynu.net",
      "port": 28181,
      "id": "dcf8e5eb-3805-3a18-8d0d-5fa0a7ddce38",
      "alterId": 0,
      "security": "auto",
      "network": "ws",
      "remarks": "台湾 C | 公益节点 直连 1倍 NF【最新网址 闪电.net】",
      "headerType": "none",
      "requestHost": "www.bing.com",
      "path": "/",
      "streamSecurity": "",
      "allowInsecure": "False",
      "configType": 1,
      "testResult": "",
      "subid": "199ab9f3-c6f5-4c95-8d87-b26a9ed0050a",
      "flow": "",
      "sni": "",
      "alpn": []
    },
    {
      "configVersion": 2,
      "address": "tw-sd-v1-01.xyx-xylo.com",
      "port": 11180,
      "id": "dcf8e5eb-3805-3a18-8d0d-5fa0a7ddce38",
      "alterId": 0,
      "security": "auto",
      "network": "ws",
      "remarks": "台湾L1 直连N1 [1.5]",
      "headerType": "none",
      "requestHost": "www.bing.com",
      "path": "/",
      "streamSecurity": "",
      "allowInsecure": "False",
      "configType": 1,
      "testResult": "",
      "subid": "199ab9f3-c6f5-4c95-8d87-b26a9ed0050a",
      "flow": "",
      "sni": "",
      "alpn": []
    },
    {
      "configVersion": 2,
      "address": "tw-sd-v1-02.xyx-xylo.com",
      "port": 11180,
      "id": "dcf8e5eb-3805-3a18-8d0d-5fa0a7ddce38",
      "alterId": 0,
      "security": "auto",
      "network": "ws",
      "remarks": "台湾L1 直连N2 [1.5]",
      "headerType": "none",
      "requestHost": "www.bing.com",
      "path": "/",
      "streamSecurity": "",
      "allowInsecure": "False",
      "configType": 1,
      "testResult": "",
      "subid": "199ab9f3-c6f5-4c95-8d87-b26a9ed0050a",
      "flow": "",
      "sni": "",
      "alpn": []
    },
    {
      "configVersion": 2,
      "address": "tw-sd-v1-03.xyx-xylo.com",
      "port": 11180,
      "id": "dcf8e5eb-3805-3a18-8d0d-5fa0a7ddce38",
      "alterId": 0,
      "security": "auto",
      "network": "ws",
      "remarks": "台湾L1 直连N3 [1.5]",
      "headerType": "none",
      "requestHost": "www.bing.com",
      "path": "/",
      "streamSecurity": "",
      "allowInsecure": "False",
      "configType": 1,
      "testResult": "",
      "subid": "199ab9f3-c6f5-4c95-8d87-b26a9ed0050a",
      "flow": "",
      "sni": "",
      "alpn": []
    },
    {
      "configVersion": 2,
      "address": "tw-l2.sd-yun.cc",
      "port": 31001,
      "id": "dcf8e5eb-3805-3a18-8d0d-5fa0a7ddce38",
      "alterId": 0,
      "security": "auto",
      "network": "ws",
      "remarks": "台湾L2 中继M1S1 [2]",
      "headerType": "none",
      "requestHost": "www.bing.com",
      "path": "/",
      "streamSecurity": "",
      "allowInsecure": "False",
      "configType": 1,
      "testResult": "",
      "subid": "199ab9f3-c6f5-4c95-8d87-b26a9ed0050a",
      "flow": "",
      "sni": "",
      "alpn": []
    },
    {
      "configVersion": 2,
      "address": "tw-l2.sd-yun.cc",
      "port": 31002,
      "id": "dcf8e5eb-3805-3a18-8d0d-5fa0a7ddce38",
      "alterId": 0,
      "security": "auto",
      "network": "ws",
      "remarks": "台湾L2 中继M1S2 [2]",
      "headerType": "none",
      "requestHost": "www.bing.com",
      "path": "/",
      "streamSecurity": "",
      "allowInsecure": "False",
      "configType": 1,
      "testResult": "",
      "subid": "199ab9f3-c6f5-4c95-8d87-b26a9ed0050a",
      "flow": "",
      "sni": "",
      "alpn": []
    },
    {
      "configVersion": 2,
      "address": "tw-l2.sd-yun.cc",
      "port": 31003,
      "id": "dcf8e5eb-3805-3a18-8d0d-5fa0a7ddce38",
      "alterId": 0,
      "security": "auto",
      "network": "ws",
      "remarks": "台湾L2 中继M1S3 [2]",
      "headerType": "none",
      "requestHost": "www.bing.com",
      "path": "/",
      "streamSecurity": "",
      "allowInsecure": "False",
      "configType": 1,
      "testResult": "",
      "subid": "199ab9f3-c6f5-4c95-8d87-b26a9ed0050a",
      "flow": "",
      "sni": "",
      "alpn": []
    },
    {
      "configVersion": 2,
      "address": "codes-nodes.sd-yun.cc",
      "port": 30001,
      "id": "dcf8e5eb-3805-3a18-8d0d-5fa0a7ddce38",
      "alterId": 0,
      "security": "auto",
      "network": "ws",
      "remarks": "应急续费节点",
      "headerType": "none",
      "requestHost": "www.bing.com",
      "path": "/",
      "streamSecurity": "",
      "allowInsecure": "False",
      "configType": 1,
      "testResult": "",
      "subid": "199ab9f3-c6f5-4c95-8d87-b26a9ed0050a",
      "flow": "",
      "sni": "",
      "alpn": []
    },
    {
      "configVersion": 2,
      "address": "sg40.freexyz.cf",
      "port": 18080,
      "id": "dcf8e5eb-3805-3a18-8d0d-5fa0a7ddce38",
      "alterId": 0,
      "security": "auto",
      "network": "ws",
      "remarks": "新加坡L1 直连N1 [1]",
      "headerType": "none",
      "requestHost": "www.bing.com",
      "path": "/",
      "streamSecurity": "",
      "allowInsecure": "False",
      "configType": 1,
      "testResult": "",
      "subid": "199ab9f3-c6f5-4c95-8d87-b26a9ed0050a",
      "flow": "",
      "sni": "",
      "alpn": []
    },
    {
      "configVersion": 2,
      "address": "sg43.freexyz.cf",
      "port": 18081,
      "id": "dcf8e5eb-3805-3a18-8d0d-5fa0a7ddce38",
      "alterId": 0,
      "security": "auto",
      "network": "ws",
      "remarks": "新加坡L1 直连N2 [1]",
      "headerType": "none",
      "requestHost": "genshin.mihoyo.com",
      "path": "/",
      "streamSecurity": "",
      "allowInsecure": "False",
      "configType": 1,
      "testResult": "",
      "subid": "199ab9f3-c6f5-4c95-8d87-b26a9ed0050a",
      "flow": "",
      "sni": "",
      "alpn": []
    },
    {
      "configVersion": 2,
      "address": "sg42.freexyz.cf",
      "port": 18081,
      "id": "dcf8e5eb-3805-3a18-8d0d-5fa0a7ddce38",
      "alterId": 0,
      "security": "auto",
      "network": "ws",
      "remarks": "新加坡L1 直连N3 [1]",
      "headerType": "none",
      "requestHost": "genshin.mihoyo.com",
      "path": "/",
      "streamSecurity": "",
      "allowInsecure": "False",
      "configType": 1,
      "testResult": "",
      "subid": "199ab9f3-c6f5-4c95-8d87-b26a9ed0050a",
      "flow": "",
      "sni": "",
      "alpn": []
    },
    {
      "configVersion": 2,
      "address": "sg02.freexyz.cf",
      "port": 18081,
      "id": "dcf8e5eb-3805-3a18-8d0d-5fa0a7ddce38",
      "alterId": 0,
      "security": "auto",
      "network": "ws",
      "remarks": "新加坡L1 直连N4 [1]",
      "headerType": "none",
      "requestHost": "www.bing.com",
      "path": "/",
      "streamSecurity": "",
      "allowInsecure": "False",
      "configType": 1,
      "testResult": "",
      "subid": "199ab9f3-c6f5-4c95-8d87-b26a9ed0050a",
      "flow": "",
      "sni": "",
      "alpn": []
    },
    {
      "configVersion": 2,
      "address": "sg-l2.plz-node.xyz",
      "port": 15030,
      "id": "dcf8e5eb-3805-3a18-8d0d-5fa0a7ddce38",
      "alterId": 0,
      "security": "auto",
      "network": "ws",
      "remarks": "新加坡L2 中继N1 [3]",
      "headerType": "none",
      "requestHost": "www.bing.com",
      "path": "/",
      "streamSecurity": "",
      "allowInsecure": "False",
      "configType": 1,
      "testResult": "",
      "subid": "199ab9f3-c6f5-4c95-8d87-b26a9ed0050a",
      "flow": "",
      "sni": "",
      "alpn": []
    },
    {
      "configVersion": 2,
      "address": "sg-l2.plz-node.xyz",
      "port": 16001,
      "id": "dcf8e5eb-3805-3a18-8d0d-5fa0a7ddce38",
      "alterId": 0,
      "security": "auto",
      "network": "ws",
      "remarks": "新加坡L2 中继N2 [3]",
      "headerType": "none",
      "requestHost": "www.bing.com",
      "path": "/",
      "streamSecurity": "",
      "allowInsecure": "False",
      "configType": 1,
      "testResult": "",
      "subid": "199ab9f3-c6f5-4c95-8d87-b26a9ed0050a",
      "flow": "",
      "sni": "",
      "alpn": []
    },
    {
      "configVersion": 2,
      "address": "sg-l2.plz-node.xyz",
      "port": 17103,
      "id": "dcf8e5eb-3805-3a18-8d0d-5fa0a7ddce38",
      "alterId": 0,
      "security": "auto",
      "network": "ws",
      "remarks": "新加坡L2 中继N3 [3]",
      "headerType": "none",
      "requestHost": "www.bing.com",
      "path": "/",
      "streamSecurity": "",
      "allowInsecure": "False",
      "configType": 1,
      "testResult": "",
      "subid": "199ab9f3-c6f5-4c95-8d87-b26a9ed0050a",
      "flow": "",
      "sni": "",
      "alpn": []
    },
    {
      "configVersion": 2,
      "address": "sg-l2.plz-node.xyz",
      "port": 13334,
      "id": "dcf8e5eb-3805-3a18-8d0d-5fa0a7ddce38",
      "alterId": 0,
      "security": "auto",
      "network": "ws",
      "remarks": "新加坡L2 中继N4 [3]",
      "headerType": "none",
      "requestHost": "www.bing.com",
      "path": "/",
      "streamSecurity": "",
      "allowInsecure": "False",
      "configType": 1,
      "testResult": "",
      "subid": "199ab9f3-c6f5-4c95-8d87-b26a9ed0050a",
      "flow": "",
      "sni": "",
      "alpn": []
    },
    {
      "configVersion": 2,
      "address": "sakura26.freexyz.cf",
      "port": 11180,
      "id": "dcf8e5eb-3805-3a18-8d0d-5fa0a7ddce38",
      "alterId": 0,
      "security": "auto",
      "network": "ws",
      "remarks": "日本L1 中继N1 [1]",
      "headerType": "none",
      "requestHost": "www.bing.com",
      "path": "/",
      "streamSecurity": "",
      "allowInsecure": "False",
      "configType": 1,
      "testResult": "",
      "subid": "199ab9f3-c6f5-4c95-8d87-b26a9ed0050a",
      "flow": "",
      "sni": "",
      "alpn": []
    },
    {
      "configVersion": 2,
      "address": "sakura23.freexyz.cf",
      "port": 11180,
      "id": "dcf8e5eb-3805-3a18-8d0d-5fa0a7ddce38",
      "alterId": 0,
      "security": "auto",
      "network": "ws",
      "remarks": "日本L1 中继N2 [1]",
      "headerType": "none",
      "requestHost": "pgc.qcdn.xiaodutv.com",
      "path": "/",
      "streamSecurity": "",
      "allowInsecure": "False",
      "configType": 1,
      "testResult": "",
      "subid": "199ab9f3-c6f5-4c95-8d87-b26a9ed0050a",
      "flow": "",
      "sni": "",
      "alpn": []
    },
    {
      "configVersion": 2,
      "address": "sakura28.freexyz.cf",
      "port": 18081,
      "id": "dcf8e5eb-3805-3a18-8d0d-5fa0a7ddce38",
      "alterId": 0,
      "security": "auto",
      "network": "ws",
      "remarks": "日本L1 中继N3 [1]",
      "headerType": "none",
      "requestHost": "www.bing.com",
      "path": "/",
      "streamSecurity": "",
      "allowInsecure": "False",
      "configType": 1,
      "testResult": "",
      "subid": "199ab9f3-c6f5-4c95-8d87-b26a9ed0050a",
      "flow": "",
      "sni": "",
      "alpn": []
    },
    {
      "configVersion": 2,
      "address": "jp-l2.sd-yun.cc",
      "port": 34081,
      "id": "dcf8e5eb-3805-3a18-8d0d-5fa0a7ddce38",
      "alterId": 0,
      "security": "auto",
      "network": "ws",
      "remarks": "日本L2 中继M1S1 [2]",
      "headerType": "none",
      "requestHost": "www.bing.com",
      "path": "/",
      "streamSecurity": "",
      "allowInsecure": "False",
      "configType": 1,
      "testResult": "",
      "subid": "199ab9f3-c6f5-4c95-8d87-b26a9ed0050a",
      "flow": "",
      "sni": "",
      "alpn": []
    },
    {
      "configVersion": 2,
      "address": "jp-l2.sd-yun.cc",
      "port": 34060,
      "id": "dcf8e5eb-3805-3a18-8d0d-5fa0a7ddce38",
      "alterId": 0,
      "security": "auto",
      "network": "ws",
      "remarks": "日本L2 中继M1S2 [2]",
      "headerType": "none",
      "requestHost": "www.bing.com",
      "path": "/",
      "streamSecurity": "",
      "allowInsecure": "False",
      "configType": 1,
      "testResult": "",
      "subid": "199ab9f3-c6f5-4c95-8d87-b26a9ed0050a",
      "flow": "",
      "sni": "",
      "alpn": []
    },
    {
      "configVersion": 2,
      "address": "jp-l2.sd-yun.cc",
      "port": 34303,
      "id": "dcf8e5eb-3805-3a18-8d0d-5fa0a7ddce38",
      "alterId": 0,
      "security": "auto",
      "network": "ws",
      "remarks": "日本L2 中继M2S1 [2]",
      "headerType": "none",
      "requestHost": "www.bing.com",
      "path": "/",
      "streamSecurity": "",
      "allowInsecure": "False",
      "configType": 1,
      "testResult": "",
      "subid": "199ab9f3-c6f5-4c95-8d87-b26a9ed0050a",
      "flow": "",
      "sni": "",
      "alpn": []
    },
    {
      "configVersion": 2,
      "address": "jp-l2-cn2.sd-yun.cc",
      "port": 34055,
      "id": "dcf8e5eb-3805-3a18-8d0d-5fa0a7ddce38",
      "alterId": 0,
      "security": "auto",
      "network": "ws",
      "remarks": "日本L2 中继N1 [3]",
      "headerType": "none",
      "requestHost": "pgc.qcdn.xiaodutv.com",
      "path": "/",
      "streamSecurity": "",
      "allowInsecure": "False",
      "configType": 1,
      "testResult": "",
      "subid": "199ab9f3-c6f5-4c95-8d87-b26a9ed0050a",
      "flow": "",
      "sni": "",
      "alpn": []
    },
    {
      "configVersion": 2,
      "address": "jp-l2-cn2.sd-yun.cc",
      "port": 34079,
      "id": "dcf8e5eb-3805-3a18-8d0d-5fa0a7ddce38",
      "alterId": 0,
      "security": "auto",
      "network": "ws",
      "remarks": "日本L2 中继N2 [3]",
      "headerType": "none",
      "requestHost": "pgc.qcdn.xiaodutv.com",
      "path": "/",
      "streamSecurity": "",
      "allowInsecure": "False",
      "configType": 1,
      "testResult": "",
      "subid": "199ab9f3-c6f5-4c95-8d87-b26a9ed0050a",
      "flow": "",
      "sni": "",
      "alpn": []
    },
    {
      "configVersion": 2,
      "address": "us01.freexyz.cf",
      "port": 8080,
      "id": "dcf8e5eb-3805-3a18-8d0d-5fa0a7ddce38",
      "alterId": 0,
      "security": "auto",
      "network": "ws",
      "remarks": "美国L1 直连N1 [1]",
      "headerType": "none",
      "requestHost": "ajax.microsoft.com",
      "path": "/",
      "streamSecurity": "",
      "allowInsecure": "False",
      "configType": 1,
      "testResult": "",
      "subid": "199ab9f3-c6f5-4c95-8d87-b26a9ed0050a",
      "flow": "",
      "sni": "",
      "alpn": []
    },
    {
      "configVersion": 2,
      "address": "206.119.184.16",
      "port": 18281,
      "id": "dcf8e5eb-3805-3a18-8d0d-5fa0a7ddce38",
      "alterId": 0,
      "security": "auto",
      "network": "ws",
      "remarks": "美国L1 直连N2 [1]",
      "headerType": "none",
      "requestHost": "www.bing.com",
      "path": "/",
      "streamSecurity": "",
      "allowInsecure": "False",
      "configType": 1,
      "testResult": "",
      "subid": "199ab9f3-c6f5-4c95-8d87-b26a9ed0050a",
      "flow": "",
      "sni": "",
      "alpn": []
    },
    {
      "configVersion": 2,
      "address": "206.119.184.2",
      "port": 18081,
      "id": "dcf8e5eb-3805-3a18-8d0d-5fa0a7ddce38",
      "alterId": 0,
      "security": "auto",
      "network": "ws",
      "remarks": "美国L1 直连N3 [1]",
      "headerType": "none",
      "requestHost": "www.bing.com",
      "path": "/",
      "streamSecurity": "",
      "allowInsecure": "False",
      "configType": 1,
      "testResult": "",
      "subid": "199ab9f3-c6f5-4c95-8d87-b26a9ed0050a",
      "flow": "",
      "sni": "",
      "alpn": []
    },
    {
      "configVersion": 2,
      "address": "206.119.184.19",
      "port": 18081,
      "id": "dcf8e5eb-3805-3a18-8d0d-5fa0a7ddce38",
      "alterId": 0,
      "security": "auto",
      "network": "ws",
      "remarks": "美国L1 直连N4 [1]",
      "headerType": "none",
      "requestHost": "www.bing.com",
      "path": "/",
      "streamSecurity": "",
      "allowInsecure": "False",
      "configType": 1,
      "testResult": "",
      "subid": "199ab9f3-c6f5-4c95-8d87-b26a9ed0050a",
      "flow": "",
      "sni": "",
      "alpn": []
    },
    {
      "configVersion": 2,
      "address": "us-l2.sd-yun.cc",
      "port": 34154,
      "id": "dcf8e5eb-3805-3a18-8d0d-5fa0a7ddce38",
      "alterId": 0,
      "security": "auto",
      "network": "ws",
      "remarks": "美国L2 中继M1S1 [2]",
      "headerType": "none",
      "requestHost": "www.bing.com",
      "path": "/",
      "streamSecurity": "",
      "allowInsecure": "False",
      "configType": 1,
      "testResult": "",
      "subid": "199ab9f3-c6f5-4c95-8d87-b26a9ed0050a",
      "flow": "",
      "sni": "",
      "alpn": []
    },
    {
      "configVersion": 2,
      "address": "us-l2.sd-yun.cc",
      "port": 34173,
      "id": "dcf8e5eb-3805-3a18-8d0d-5fa0a7ddce38",
      "alterId": 0,
      "security": "auto",
      "network": "ws",
      "remarks": "美国L2 中继M1S2 [2]",
      "headerType": "none",
      "requestHost": "www.bing.com",
      "path": "/",
      "streamSecurity": "",
      "allowInsecure": "False",
      "configType": 1,
      "testResult": "",
      "subid": "199ab9f3-c6f5-4c95-8d87-b26a9ed0050a",
      "flow": "",
      "sni": "",
      "alpn": []
    },
    {
      "configVersion": 2,
      "address": "us-l2.sd-yun.cc",
      "port": 34174,
      "id": "dcf8e5eb-3805-3a18-8d0d-5fa0a7ddce38",
      "alterId": 0,
      "security": "auto",
      "network": "ws",
      "remarks": "美国L2 中继M1S3 [2]",
      "headerType": "none",
      "requestHost": "www.bing.com",
      "path": "/",
      "streamSecurity": "",
      "allowInsecure": "False",
      "configType": 1,
      "testResult": "",
      "subid": "199ab9f3-c6f5-4c95-8d87-b26a9ed0050a",
      "flow": "",
      "sni": "",
      "alpn": []
    },
    {
      "configVersion": 2,
      "address": "us-l2-cn2.sd-yun.cc",
      "port": 10015,
      "id": "dcf8e5eb-3805-3a18-8d0d-5fa0a7ddce38",
      "alterId": 0,
      "security": "auto",
      "network": "ws",
      "remarks": "美国L2 中继N1 [3]",
      "headerType": "none",
      "requestHost": "www.bing.com",
      "path": "/",
      "streamSecurity": "",
      "allowInsecure": "False",
      "configType": 1,
      "testResult": "",
      "subid": "199ab9f3-c6f5-4c95-8d87-b26a9ed0050a",
      "flow": "",
      "sni": "",
      "alpn": []
    },
    {
      "configVersion": 2,
      "address": "us-l2-cn2.sd-yun.cc",
      "port": 20008,
      "id": "dcf8e5eb-3805-3a18-8d0d-5fa0a7ddce38",
      "alterId": 0,
      "security": "auto",
      "network": "ws",
      "remarks": "美国L2 中继N2 [3]",
      "headerType": "none",
      "requestHost": "www.bing.com",
      "path": "/",
      "streamSecurity": "",
      "allowInsecure": "False",
      "configType": 1,
      "testResult": "",
      "subid": "199ab9f3-c6f5-4c95-8d87-b26a9ed0050a",
      "flow": "",
      "sni": "",
      "alpn": []
    },
    {
      "configVersion": 2,
      "address": "hk-l2-m.sd-yun.cc",
      "port": 34084,
      "id": "dcf8e5eb-3805-3a18-8d0d-5fa0a7ddce38",
      "alterId": 0,
      "security": "auto",
      "network": "ws",
      "remarks": "香港L2 中继M1S1 [3]",
      "headerType": "none",
      "requestHost": "ajax.microsoft.com",
      "path": "/",
      "streamSecurity": "",
      "allowInsecure": "False",
      "configType": 1,
      "testResult": "",
      "subid": "199ab9f3-c6f5-4c95-8d87-b26a9ed0050a",
      "flow": "",
      "sni": "",
      "alpn": []
    },
    {
      "configVersion": 2,
      "address": "hk-l2-m.sd-yun.cc",
      "port": 34149,
      "id": "dcf8e5eb-3805-3a18-8d0d-5fa0a7ddce38",
      "alterId": 0,
      "security": "auto",
      "network": "ws",
      "remarks": "香港L2 中继M1S2 [3]",
      "headerType": "none",
      "requestHost": "ajax.microsoft.com",
      "path": "/",
      "streamSecurity": "",
      "allowInsecure": "False",
      "configType": 1,
      "testResult": "",
      "subid": "199ab9f3-c6f5-4c95-8d87-b26a9ed0050a",
      "flow": "",
      "sni": "",
      "alpn": []
    },
    {
      "configVersion": 2,
      "address": "hk-l2-cn2.sd-yun.cc",
      "port": 28104,
      "id": "dcf8e5eb-3805-3a18-8d0d-5fa0a7ddce38",
      "alterId": 0,
      "security": "auto",
      "network": "ws",
      "remarks": "香港L2 中继N1 [3]",
      "headerType": "none",
      "requestHost": "ajax.microsoft.com",
      "path": "/",
      "streamSecurity": "",
      "allowInsecure": "False",
      "configType": 1,
      "testResult": "",
      "subid": "199ab9f3-c6f5-4c95-8d87-b26a9ed0050a",
      "flow": "",
      "sni": "",
      "alpn": []
    },
    {
      "configVersion": 2,
      "address": "hk-l2-cn2.sd-yun.cc",
      "port": 32002,
      "id": "dcf8e5eb-3805-3a18-8d0d-5fa0a7ddce38",
      "alterId": 0,
      "security": "auto",
      "network": "ws",
      "remarks": "香港L2 中继N2 [3]",
      "headerType": "none",
      "requestHost": "www.bing.com",
      "path": "/",
      "streamSecurity": "",
      "allowInsecure": "False",
      "configType": 1,
      "testResult": "",
      "subid": "199ab9f3-c6f5-4c95-8d87-b26a9ed0050a",
      "flow": "",
      "sni": "",
      "alpn": []
    },
    {
      "configVersion": 2,
      "address": "hk-l2-cn2.sd-yun.cc",
      "port": 20004,
      "id": "dcf8e5eb-3805-3a18-8d0d-5fa0a7ddce38",
      "alterId": 0,
      "security": "auto",
      "network": "ws",
      "remarks": "香港L2 中继N3 [3]",
      "headerType": "none",
      "requestHost": "ajax.microsoft.com",
      "path": "/",
      "streamSecurity": "",
      "allowInsecure": "False",
      "configType": 1,
      "testResult": "",
      "subid": "199ab9f3-c6f5-4c95-8d87-b26a9ed0050a",
      "flow": "",
      "sni": "",
      "alpn": []
    },
    {
      "configVersion": 2,
      "address": "ml-l1.sd-yun.cc",
      "port": 20001,
      "id": "dcf8e5eb-3805-3a18-8d0d-5fa0a7ddce38",
      "alterId": 0,
      "security": "auto",
      "network": "ws",
      "remarks": "马来西亚L1 中继N1 [0.3]",
      "headerType": "none",
      "requestHost": "www.bing.com",
      "path": "/",
      "streamSecurity": "",
      "allowInsecure": "False",
      "configType": 1,
      "testResult": "",
      "subid": "199ab9f3-c6f5-4c95-8d87-b26a9ed0050a",
      "flow": "",
      "sni": "",
      "alpn": []
    },
    {
      "configVersion": 2,
      "address": "ml-l1.sd-yun.cc",
      "port": 20002,
      "id": "dcf8e5eb-3805-3a18-8d0d-5fa0a7ddce38",
      "alterId": 0,
      "security": "auto",
      "network": "ws",
      "remarks": "马来西亚L1 中继N2 [0.3]",
      "headerType": "none",
      "requestHost": "www.bing.com",
      "path": "/",
      "streamSecurity": "",
      "allowInsecure": "False",
      "configType": 1,
      "testResult": "",
      "subid": "199ab9f3-c6f5-4c95-8d87-b26a9ed0050a",
      "flow": "",
      "sni": "",
      "alpn": []
    },
    {
      "configVersion": 2,
      "address": "ml-l2.sd-yun.cc",
      "port": 20003,
      "id": "dcf8e5eb-3805-3a18-8d0d-5fa0a7ddce38",
      "alterId": 0,
      "security": "auto",
      "network": "ws",
      "remarks": "马来西亚L2 中继N1 [0.2]\t",
      "headerType": "none",
      "requestHost": "www.bing.com",
      "path": "/",
      "streamSecurity": "",
      "allowInsecure": "False",
      "configType": 1,
      "testResult": "",
      "subid": "199ab9f3-c6f5-4c95-8d87-b26a9ed0050a",
      "flow": "",
      "sni": "",
      "alpn": []
    }
  ],
  "muxEnabled": false,
  "kcpItem": {
    "mtu": 1350,
    "tti": 50,
    "uplinkCapacity": 12,
    "downlinkCapacity": 100,
    "congestion": false,
    "readBufferSize": 2,
    "writeBufferSize": 2
  },
  "sysProxyType": 1,
  "allowLANConn": false,
  "enableStatistics": false,
  "keepOlderDedupl": false,
  "statisticsFreshRate": 2000,
  "remoteDNS": null,
  "defAllowInsecure": false,
  "subItem": [
    {
      "id": "199ab9f3-c6f5-4c95-8d87-b26a9ed0050a",
      "remarks": "闪电付费",
      "url": "https://subscribe.receivei.com/link/rUR7tVpWvwVmnIYE?sub=3",
      "enabled": true,
      "userAgent": ""
    }
  ],
  "uiItem": {
    "mainSize": "968, 632",
    "mainLvColWidth": {
      "def": 30,
      "configType": 80,
      "remarks": 273,
      "address": 120,
      "port": 50,
      "security": 90,
      "network": 70,
      "streamSecurity": 70,
      "subRemarks": 72,
      "testResult": 316
    }
  },
  "domainStrategy": "IPIfNonMatch",
  "domainMatcher": "mph",
  "routingIndex": 1,
  "routings": [
    {
      "remarks": "绕过大陆(Whitelist)",
      "url": "",
      "rules": [
        {
          "type": null,
          "port": null,
          "inboundTag": null,
          "outboundTag": "direct",
          "ip": null,
          "domain": [
            "domain:example-example.com",
            "domain:example-example2.com"
          ],
          "protocol": null,
          "enabled": true
        },
        {
          "type": null,
          "port": null,
          "inboundTag": null,
          "outboundTag": "block",
          "ip": null,
          "domain": [
            "geosite:category-ads-all"
          ],
          "protocol": null,
          "enabled": true
        },
        {
          "type": null,
          "port": null,
          "inboundTag": null,
          "outboundTag": "direct",
          "ip": null,
          "domain": [
            "geosite:cn"
          ],
          "protocol": null,
          "enabled": true
        },
        {
          "type": null,
          "port": null,
          "inboundTag": null,
          "outboundTag": "direct",
          "ip": [
            "geoip:private",
            "geoip:cn"
          ],
          "domain": null,
          "protocol": null,
          "enabled": true
        },
        {
          "type": null,
          "port": "0-65535",
          "inboundTag": null,
          "outboundTag": "proxy",
          "ip": null,
          "domain": null,
          "protocol": null,
          "enabled": true
        }
      ],
      "enabled": true,
      "locked": false,
      "customIcon": null
    },
    {
      "remarks": "黑名单(Blacklist)",
      "url": "",
      "rules": [
        {
          "type": null,
          "port": null,
          "inboundTag": null,
          "outboundTag": "direct",
          "ip": null,
          "domain": null,
          "protocol": [
            "bittorrent"
          ],
          "enabled": true
        },
        {
          "type": null,
          "port": null,
          "inboundTag": null,
          "outboundTag": "block",
          "ip": null,
          "domain": [
            "geosite:category-ads-all"
          ],
          "protocol": null,
          "enabled": true
        },
        {
          "type": null,
          "port": null,
          "inboundTag": null,
          "outboundTag": "proxy",
          "ip": [
            "geoip:telegram"
          ],
          "domain": [
            "geosite:gfw",
            "geosite:greatfire",
            "geosite:tld-!cn"
          ],
          "protocol": null,
          "enabled": true
        },
        {
          "type": null,
          "port": "0-65535",
          "inboundTag": null,
          "outboundTag": "direct",
          "ip": null,
          "domain": null,
          "protocol": null,
          "enabled": true
        }
      ],
      "enabled": true,
      "locked": false,
      "customIcon": null
    },
    {
      "remarks": "全局(Global)",
      "url": "",
      "rules": [
        {
          "type": null,
          "port": "0-65535",
          "inboundTag": null,
          "outboundTag": "proxy",
          "ip": null,
          "domain": null,
          "protocol": null,
          "enabled": true
        }
      ],
      "enabled": true,
      "locked": false,
      "customIcon": null
    },
    {
      "remarks": "locked",
      "url": "",
      "rules": [
        {
          "type": null,
          "port": null,
          "inboundTag": null,
          "outboundTag": "proxy",
          "ip": [],
          "domain": [
            "geosite:google"
          ],
          "protocol": null,
          "enabled": true
        },
        {
          "type": null,
          "port": null,
          "inboundTag": null,
          "outboundTag": "direct",
          "ip": [],
          "domain": [
            "domain:example-example.com",
            "domain:example-example2.com"
          ],
          "protocol": null,
          "enabled": true
        },
        {
          "type": null,
          "port": null,
          "inboundTag": null,
          "outboundTag": "block",
          "ip": [],
          "domain": [
            "geosite:category-ads-all"
          ],
          "protocol": null,
          "enabled": true
        }
      ],
      "enabled": true,
      "locked": true,
      "customIcon": null
    }
  ],
  "enableRoutingAdvanced": true,
  "coreType": 0,
  "ignoreGeoUpdateCore": false,
  "systemProxyExceptions": null,
  "autoUpdateInterval": 0,
  "constItem": {
    "speedTestUrl": "http://cachefly.cachefly.net/10mb.test",
    "speedPingTestUrl": "https://www.google.com/generate_204",
    "defIEProxyExceptions": "localhost;127.*;10.*;172.16.*;172.17.*;172.18.*;172.19.*;172.20.*;172.21.*;172.22.*;172.23.*;172.24.*;172.25.*;172.26.*;172.27.*;172.28.*;172.29.*;172.30.*;172.31.*;192.168.*"
  }
}